main.py
setup.py
lanm_neo.egg-info/PKG-INFO
lanm_neo.egg-info/SOURCES.txt
lanm_neo.egg-info/dependency_links.txt
lanm_neo.egg-info/requires.txt
lanm_neo.egg-info/top_level.txt